pytemidi/__init__.py
pytemidi/pytemidi.py
pytemidi-0.0.5.dist-info/LICENSE.txt
pytemidi-0.0.5.dist-info/METADATA
pytemidi-0.0.5.dist-info/WHEEL
pytemidi-0.0.5.dist-info/top_level.txt
pytemidi-0.0.5.dist-info/RECORD
